[
    {"userID": 3, "eventID": 1},
    {"userID": 59, "eventID": 3},
    {"userID": 45, "eventID": 10},
    {"userID": 5, "eventID": 1},
    {"userID": 83, "eventID": 9},
    {"userID": 10, "eventID": 6},
    {"userID": 60, "eventID": 10},
    {"userID": 44, "eventID": 5},
    {"userID": 35, "eventID": 5},
    {"userID": 15, "eventID": 2},
    {"userID": 81, "eventID": 5},
    {"userID": 64, "eventID": 4},
    {"userID": 23, "eventID": 3},
    {"userID": 91, "eventID": 3},
    {"userID": 22, "eventID": 10},
    {"userID": 58, "eventID": 9},
    {"userID": 8, "eventID": 5},
    {"userID": 46, "eventID": 4},
    {"userID": 6, "eventID": 1},
    {"userID": 63, "eventID": 5},
    {"userID": 54, "eventID": 2},
    {"userID": 84, "eventID": 3},
    {"userID": 21, "eventID": 5},
    {"userID": 12, "eventID": 2},
    {"userID": 54, "eventID": 5},
    {"userID": 53, "eventID": 9},
    {"userID": 34, "eventID": 5},
    {"userID": 4, "eventID": 7},
    {"userID": 4, "eventID": 4},
    {"userID": 50, "eventID": 7},
    {"userID": 43, "eventID": 7},
    {"userID": 15, "eventID": 6},
    {"userID": 26, "eventID": 6},
    {"userID": 81, "eventID": 6},
    {"userID": 82, "eventID": 2},
    {"userID": 7, "eventID": 8},
    {"userID": 49, "eventID": 8},
    {"userID": 63, "eventID": 7},
    {"userID": 64, "eventID": 2},
    {"userID": 86, "eventID": 2}
]